gmsh_scripts/__init__.py
gmsh_scripts/__main__.py
gmsh_scripts/factory.py
gmsh_scripts/load.py
gmsh_scripts/plot.py
gmsh_scripts/registry.py
gmsh_scripts/run.py
gmsh_scripts/block/__init__.py
gmsh_scripts/block/block.py
gmsh_scripts/block/half_layer.py
gmsh_scripts/block/layer.py
gmsh_scripts/block/matrix.py
gmsh_scripts/block/polyhedron.py
gmsh_scripts/block/quarter_layer.py
gmsh_scripts/boolean/__init__.py
gmsh_scripts/boolean/boolean.py
gmsh_scripts/coordinate_system/__init__.py
gmsh_scripts/coordinate_system/coordinate_system.py
gmsh_scripts/entity/__init__.py
gmsh_scripts/entity/curve.py
gmsh_scripts/entity/curve_loop.py
gmsh_scripts/entity/point.py
gmsh_scripts/entity/surface.py
gmsh_scripts/entity/surface_loop.py
gmsh_scripts/entity/volume.py
gmsh_scripts/optimize/__init__.py
gmsh_scripts/optimize/optimize.py
gmsh_scripts/parse/__init__.py
gmsh_scripts/parse/parse.py
gmsh_scripts/quadrate/__init__.py
gmsh_scripts/quadrate/quadrate.py
gmsh_scripts/refine/__init__.py
gmsh_scripts/refine/refine.py
gmsh_scripts/size/__init__.py
gmsh_scripts/size/size.py
gmsh_scripts/smooth/__init__.py
gmsh_scripts/smooth/smooth.py
gmsh_scripts/strategy/__init__.py
gmsh_scripts/strategy/strategy.py
gmsh_scripts/structure/__init__.py
gmsh_scripts/structure/structure.py
gmsh_scripts/support/__init__.py
gmsh_scripts/support/support.py
gmsh_scripts/transform/__init__.py
gmsh_scripts/transform/transform.py
gmsh_scripts/utils/__init__.py
gmsh_scripts/utils/obj2gmsh.py
gmsh_scripts/zone/__init__.py
gmsh_scripts/zone/zone.py
gmsh_scripts-0.4.8.dist-info/licenses/LICENSE.txt
gmsh_scripts-0.4.8.dist-info/METADATA
gmsh_scripts-0.4.8.dist-info/WHEEL
gmsh_scripts-0.4.8.dist-info/top_level.txt
gmsh_scripts-0.4.8.dist-info/RECORD
