Metadata-Version: 2.4
Name: gmsh-scripts
Version: 0.4.8
Summary: Scripts for GMSH mesh generator
Author: Vladimir Lefèvre
Author-email: Roman Pashkovsky <romapasky@gmail.com>
Maintainer: Vladimir Lefèvre
Maintainer-email: Roman Pashkovsky <romapasky@gmail.com>
License-Expression: GPL-2.0-or-later
Project-URL: Homepage, https://github.com/romanzes637/gmsh_scripts
Project-URL: Documentation, https://gmsh-scripts.readthedocs.io/en/latest/
Keywords: mesh,gmsh
Classifier: Operating System :: OS Independent
Classifier: Programming Language :: Python :: 3
Requires-Python: >=3.6
License-File: LICENSE.txt
Requires-Dist: gmsh
Requires-Dist: numpy
Requires-Dist: pyyaml
Provides-Extra: viz
Requires-Dist: pyvis; extra == "viz"
Dynamic: license-file
